pyintelowl/__init__.py
pyintelowl/exceptions.py
pyintelowl/main.py
pyintelowl/pyintelowl.py
pyintelowl/version.py
pyintelowl/cli/__init__.py
pyintelowl/cli/_jobs_utils.py
pyintelowl/cli/_utils.py
pyintelowl/cli/analyse.py
pyintelowl/cli/commands.py
pyintelowl/cli/config.py
pyintelowl/cli/domain_checkers.py
pyintelowl/cli/investigations.py
pyintelowl/cli/jobs.py
pyintelowl/cli/playbooks.py
pyintelowl/cli/tags.py
tests/__init__.py
tests/mocked_requests.py
tests/test_general.py
tests/test_investigations.py
tests/test_jobs.py
tests/test_playbooks.py
tests/test_tags.py
tests/utils.py
pyintelowl-5.1.0.dist-info/LICENSE
pyintelowl-5.1.0.dist-info/METADATA
pyintelowl-5.1.0.dist-info/WHEEL
pyintelowl-5.1.0.dist-info/entry_points.txt
pyintelowl-5.1.0.dist-info/top_level.txt
pyintelowl-5.1.0.dist-info/RECORD
