Metadata-Version: 2.1
Name: pyintelowl
Version: 5.1.0
Summary: Robust Python SDK and CLI for IntelOwl's API
Home-page: https://github.com/intelowlproject/pyintelowl
Author: Matteo Lodi
Project-URL: Documentation, https://github.com/intelowlproject/pyintelowl
Project-URL: Funding, https://opencollective.com/intelowl-project
Project-URL: Source, https://github.com/intelowlproject/pyintelowl
Project-URL: Tracker, https://github.com/intelowlproject/pyintelowl/issues
Keywords: intelowl sdk python command line osint threat intel malware
Classifier: Development Status :: 5 - Production/Stable
Classifier: Intended Audience :: Developers
Classifier: Environment :: Web Environment
Classifier: License :: OSI Approved :: GNU Affero General Public License v3 or later (AGPLv3+)
Classifier: Programming Language :: Python :: 3.9
Classifier: Programming Language :: Python :: 3.10
Classifier: Programming Language :: Python :: 3.11
Classifier: Topic :: Software Development :: Libraries :: Python Modules
Requires-Python: >=3.9
License-File: LICENSE
Requires-Dist: requests>=2.28
Requires-Dist: geocoder>=1.38
Requires-Dist: click>=7.0
Requires-Dist: rich>=12.5.1
Requires-Dist: click-creds>=0.0.3
Requires-Dist: typing_extensions>=4.3.0
Provides-Extra: dev
Requires-Dist: black==24.8.0; extra == "dev"
Requires-Dist: flake8==7.1.1; extra == "dev"
Requires-Dist: isort==5.12.0; extra == "dev"
Requires-Dist: pre-commit==4.0.1; extra == "dev"
Requires-Dist: tox==3.25.1; extra == "dev"
Requires-Dist: tox-gh-actions==2.9.1; extra == "dev"
Requires-Dist: codecov==2.1.13; extra == "dev"
Requires-Dist: requests>=2.28; extra == "dev"
Requires-Dist: geocoder>=1.38; extra == "dev"
Requires-Dist: click>=7.0; extra == "dev"
Requires-Dist: rich>=12.5.1; extra == "dev"
Requires-Dist: click-creds>=0.0.3; extra == "dev"
Requires-Dist: typing_extensions>=4.3.0; extra == "dev"
Provides-Extra: test
Requires-Dist: black==24.8.0; extra == "test"
Requires-Dist: flake8==7.1.1; extra == "test"
Requires-Dist: isort==5.12.0; extra == "test"
Requires-Dist: pre-commit==4.0.1; extra == "test"
Requires-Dist: tox==3.25.1; extra == "test"
Requires-Dist: tox-gh-actions==2.9.1; extra == "test"
Requires-Dist: codecov==2.1.13; extra == "test"
Requires-Dist: requests>=2.28; extra == "test"
Requires-Dist: geocoder>=1.38; extra == "test"
Requires-Dist: click>=7.0; extra == "test"
Requires-Dist: rich>=12.5.1; extra == "test"
Requires-Dist: click-creds>=0.0.3; extra == "test"
Requires-Dist: typing_extensions>=4.3.0; extra == "test"
